ariadne_graphql_proxy/__init__.py
ariadne_graphql_proxy/context_value.py
ariadne_graphql_proxy/copy.py
ariadne_graphql_proxy/errors.py
ariadne_graphql_proxy/foreign_key_resolver.py
ariadne_graphql_proxy/get_operation.py
ariadne_graphql_proxy/merge.py
ariadne_graphql_proxy/narrow_graphql_query.py
ariadne_graphql_proxy/proxy_resolver.py
ariadne_graphql_proxy/proxy_root_value.py
ariadne_graphql_proxy/proxy_schema.py
ariadne_graphql_proxy/py.typed
ariadne_graphql_proxy/query_filter.py
ariadne_graphql_proxy/remote_schema.py
ariadne_graphql_proxy/resolvers.py
ariadne_graphql_proxy/selections.py
ariadne_graphql_proxy/standard_types.py
ariadne_graphql_proxy/str_to_field.py
ariadne_graphql_proxy/unwrap_type.py
ariadne_graphql_proxy/cache/__init__.py
ariadne_graphql_proxy/cache/backend.py
ariadne_graphql_proxy/cache/cache_key.py
ariadne_graphql_proxy/cache/cached_resolver.py
ariadne_graphql_proxy/cache/serializer.py
ariadne_graphql_proxy/cache/simple_cached_resolver.py
ariadne_graphql_proxy/contrib/__init__.py
ariadne_graphql_proxy/contrib/aws/__init__.py
ariadne_graphql_proxy/contrib/aws/cache_backend.py
ariadne_graphql_proxy/contrib/cloudflare/__init__.py
ariadne_graphql_proxy/contrib/cloudflare/cache_backend.py
ariadne_graphql_proxy/contrib/imgix/__init__.py
ariadne_graphql_proxy/contrib/imgix/query_params_resolver.py
ariadne_graphql_proxy-0.5.0.dist-info/METADATA
ariadne_graphql_proxy-0.5.0.dist-info/WHEEL
ariadne_graphql_proxy-0.5.0.dist-info/licenses/LICENSE
ariadne_graphql_proxy-0.5.0.dist-info/RECORD
