Metadata-Version: 2.4
Name: ariadne-graphql-proxy
Version: 0.5.0
Summary: Ariadne toolkit for building GraphQL proxies.
Project-URL: Homepage, https://ariadnegraphql.org/
Project-URL: Repository, https://github.com/mirumee/ariadne-graphql-proxy
Project-URL: Bug Tracker, https://github.com/mirumee/ariadne-graphql-proxy/issues
Project-URL: Community, https://github.com/mirumee/ariadne/discussions
Project-URL: Twitter, https://twitter.com/AriadneGraphQL
Author-email: Mirumee Software <hello@mirumee.com>
License: BSD 3-Clause License
License-File: LICENSE
Classifier: Development Status :: 4 - Beta
Classifier: Intended Audience :: Developers
Classifier: License :: OSI Approved :: BSD License
Classifier: Operating System :: OS Independent
Classifier: Programming Language :: Python
Classifier: Programming Language :: Python :: 3.10
Classifier: Programming Language :: Python :: 3.11
Classifier: Topic :: Software Development :: Libraries :: Python Modules
Requires-Dist: ariadne>=0.23.0
Requires-Dist: graphql-core<3.3,>=3.2.0
Requires-Dist: httpx
Provides-Extra: aws
Requires-Dist: asgiref; extra == 'aws'
Requires-Dist: boto3; extra == 'aws'
Provides-Extra: orjson
Requires-Dist: orjson; extra == 'orjson'
Provides-Extra: test
Requires-Dist: black; extra == 'test'
Requires-Dist: freezegun; extra == 'test'
Requires-Dist: moto[dynamodb]; extra == 'test'
Requires-Dist: mypy; extra == 'test'
Requires-Dist: pytest; extra == 'test'
Requires-Dist: pytest-asyncio; extra == 'test'
Requires-Dist: pytest-httpx; extra == 'test'
Requires-Dist: pytest-mock; extra == 'test'
Requires-Dist: ruff; extra == 'test'
